pymodaq_plugins_mock/__init__.py
pymodaq_plugins_mock/utils.py
pymodaq_plugins_mock/daq_move_plugins/__init__.py
pymodaq_plugins_mock/daq_move_plugins/daq_move_LECODirector.py
pymodaq_plugins_mock/daq_move_plugins/daq_move_Mock.py
pymodaq_plugins_mock/daq_move_plugins/daq_move_TCPServer.py
pymodaq_plugins_mock/daq_viewer_plugins/__init__.py
pymodaq_plugins_mock/daq_viewer_plugins/plugins_0D/__init__.py
pymodaq_plugins_mock/daq_viewer_plugins/plugins_0D/daq_0Dviewer_LECODirector.py
pymodaq_plugins_mock/daq_viewer_plugins/plugins_0D/daq_0Dviewer_Mock.py
pymodaq_plugins_mock/daq_viewer_plugins/plugins_0D/daq_0Dviewer_TCPServer.py
pymodaq_plugins_mock/daq_viewer_plugins/plugins_1D/__init__.py
pymodaq_plugins_mock/daq_viewer_plugins/plugins_1D/daq_1Dviewer_LECODirector.py
pymodaq_plugins_mock/daq_viewer_plugins/plugins_1D/daq_1Dviewer_Mock.py
pymodaq_plugins_mock/daq_viewer_plugins/plugins_1D/daq_1Dviewer_TCPServer.py
pymodaq_plugins_mock/daq_viewer_plugins/plugins_2D/__init__.py
pymodaq_plugins_mock/daq_viewer_plugins/plugins_2D/daq_2Dviewer_LECODirector.py
pymodaq_plugins_mock/daq_viewer_plugins/plugins_2D/daq_2Dviewer_Mock.py
pymodaq_plugins_mock/daq_viewer_plugins/plugins_2D/daq_2Dviewer_TCPServer.py
pymodaq_plugins_mock/daq_viewer_plugins/plugins_ND/__init__.py
pymodaq_plugins_mock/daq_viewer_plugins/plugins_ND/daq_NDviewer_Mock.py
pymodaq_plugins_mock/extensions/__init__.py
pymodaq_plugins_mock/hardware/__init__.py
pymodaq_plugins_mock/hardware/wrapper.py
pymodaq_plugins_mock/models/__init__.py
pymodaq_plugins_mock/resources/__init__.py
pymodaq_plugins_mock/resources/config_template.toml
pymodaq_plugins_mock-5.0.10.dist-info/METADATA
pymodaq_plugins_mock-5.0.10.dist-info/WHEEL
pymodaq_plugins_mock-5.0.10.dist-info/entry_points.txt
pymodaq_plugins_mock-5.0.10.dist-info/licenses/LICENSE
pymodaq_plugins_mock-5.0.10.dist-info/RECORD
